{
    "vnfds": [
        {
            "service_types": [
                {
                    "service_type": "vnfd",
                    "id": "ca0d8667-ce35-4f7a-9744-ac4bc7d5579d"
                }
            ],
            "description": "Sample",
            "tenant_id": "689708956a2d4ae0a27120d3aca6a560",
            "created_at": "2016-10-20 07:38:54",
            "updated_at": null,
            "attributes": {
                "vnfd": "description: Demo example\nmetadata: {template_name: sample-tosca-vnfd}\ntopology_template:\n  node_templates:\n    CP1:\n      properties: {anti_spoofing_protection: false, management: true, order: 0}\n      requirements:\n      - virtualLink: {node: VL1}\n      - virtualBinding: {node: VDU1}\n      type: tosca.nodes.nfv.CP.Tacker\n    VDU1:\n      capabilities:\n        nfv_compute:\n          properties: {disk_size: 1 GB, mem_size: 512 MB, num_cpus: 1}\n      properties: {image: cirros-0.4.0-x86_64-disk}\n      type: tosca.nodes.nfv.VDU.Tacker\n    VL1:\n      properties: {network_name: net_mgmt, vendor: Tacker}\n      type: tosca.nodes.nfv.VL\ntosca_definitions_version: tosca_simple_profile_for_nfv_1_0_0\n"
            },
            "id": "0fb827e7-32b0-4e5b-b300-e1b1dce8a831",
            "name": "vnfd-sample",
            "template_source": "onboarded or inline"
        }
    ]
}
